README.md
setup.py
pulumi_docker_buildkit/__init__.py
pulumi_docker_buildkit/_inputs.py
pulumi_docker_buildkit/_utilities.py
pulumi_docker_buildkit/image.py
pulumi_docker_buildkit/provider.py
pulumi_docker_buildkit/pulumi-plugin.json
pulumi_docker_buildkit/py.typed
pulumi_docker_buildkit.egg-info/PKG-INFO
pulumi_docker_buildkit.egg-info/SOURCES.txt
pulumi_docker_buildkit.egg-info/dependency_links.txt
pulumi_docker_buildkit.egg-info/not-zip-safe
pulumi_docker_buildkit.egg-info/requires.txt
pulumi_docker_buildkit.egg-info/top_level.txt