Metadata-Version: 2.1
Name: pulumi-docker-buildkit
Version: 0.1.14
Summary: A Pulumi package for building Docker images with Buildkit.
Home-page: UNKNOWN
License: Apache-2.0
Project-URL: Repository, https://github.com/MaterializeInc/pulumi-docker-buildkit
Platform: UNKNOWN
